oaspy/__init__.py
oaspy/converter.py
oaspy/main.py
oaspy/utils.py
oaspy/insomnia/__init__.py
oaspy/insomnia/get_info.py
oaspy/insomnia/insomnia_v4.py
oaspy/insomnia/openapi_v30x.py
oaspy/insomnia/openapi_v31x.py
oaspy/openapi/__init__.py
oaspy/openapi/generate.py
oaspy/openapi/httpcodes.py
oaspy/openapi/validate_export.py
oaspy/openapi/schemas/__init__.py
oaspy/openapi/schemas/openapi_v3.0x.json
oaspy/openapi/schemas/openapi_v3.1x.json
oaspy/yaak/__init__.py
oaspy/yaak/get_info.py
oaspy/yaak/openapi_v30x.py
oaspy/yaak/yaak_v4.py
oaspy-2025.12.26.dist-info/entry_points.txt
oaspy-2025.12.26.dist-info/licenses/LICENSE
oaspy-2025.12.26.dist-info/WHEEL
oaspy-2025.12.26.dist-info/METADATA
oaspy-2025.12.26.dist-info/RECORD
