Metadata-Version: 2.4
Name: oaspy
Version: 2025.12.26
Summary: oaspy is a quick-and-dirty tool to generate an OpenApi 3.x specification from an insomnia V4 collections.
Keywords: oaspy,insomnia,openapi,converter
Author-email: Jorge Brunal Pérez <diniremix@gmail.com>, Gabriel Jimenez <gabrieljfpk@gmail.com>
Requires-Python: >=3.10,<3.12
Classifier: License :: OSI Approved :: MIT License
Classifier: Operating System :: OS Independent
Classifier: Programming Language :: Python
Classifier: Programming Language :: Python :: 3.10
Classifier: Programming Language :: Python :: 3.11
Classifier: Development Status :: 4 - Beta
Classifier: Environment :: Console
Classifier: Topic :: Software Development :: Libraries :: Python Modules
Classifier: Topic :: Utilities
Classifier: Topic :: File Formats :: JSON :: JSON Schema
License-File: LICENSE
Requires-Dist: click~=8.3.0
Requires-Dist: jsonschema[format]~=4.25.1
Requires-Dist: orjson~=3.11.4
Requires-Dist: jmespath~=1.0.1
Requires-Dist: genson~=1.3.0
Requires-Dist: jsf~=0.11.2
Requires-Dist: flit ; extra == "build"
Requires-Dist: flit_core ; extra == "build"
Requires-Dist: ruff~=0.14.3 ; extra == "dev"
Project-URL: Changelog, https://gitlab.com/HomeInside/oaspy/-/blob/master/CHANGELOG.md
Project-URL: Documentation, https://gitlab.com/HomeInside/oaspy
Project-URL: Homepage, https://gitlab.com/HomeInside/oaspy
Project-URL: Issues, https://gitlab.com/HomeInside/oaspy/-/issues
Project-URL: Repository, https://gitlab.com/HomeInside/oaspy.git
Provides-Extra: build
Provides-Extra: dev
